interview_eval/__init__.py
interview_eval/cli.py
interview_eval/decontaminate.py
interview_eval/interview.py
interview_eval/utils.py
interview_eval-0.1.3.dist-info/METADATA
interview_eval-0.1.3.dist-info/WHEEL
interview_eval-0.1.3.dist-info/entry_points.txt
interview_eval-0.1.3.dist-info/top_level.txt
interview_eval-0.1.3.dist-info/RECORD
