Metadata-Version: 2.1
Name: interview-eval
Version: 0.1.3
Author-email: Juyoung Suk <juyoung@kaist.ac.kr>
Requires-Python: >=3.10
Requires-Dist: black>=24.10.0
Requires-Dist: click>=8.1.7
Requires-Dist: isort>=5.13.2
Requires-Dist: openai>=1.55.2
Requires-Dist: python-dotenv>=1.0.1
Requires-Dist: pyyaml>=6.0.2
Requires-Dist: rich>=13.9.4
